grg_pheno_sim/__init__.py
grg_pheno_sim/binary_phenotype.py
grg_pheno_sim/effect_size.py
grg_pheno_sim/model.py
grg_pheno_sim/multi_grg_phenotype.py
grg_pheno_sim/noise_sim.py
grg_pheno_sim/normalization.py
grg_pheno_sim/ops_scipy.py
grg_pheno_sim/phenotype.py
grg_pheno_sim/split.py
grg_pheno_sim/validation.py
grg_pheno_sim-1.4.dist-info/licenses/LICENSE
test_phenotype_sim/__init__.py
test_phenotype_sim/effect_size_test.py
test_phenotype_sim/genetic_value_test.py
test_phenotype_sim/phenotype_test.py
grg_pheno_sim-1.4.dist-info/METADATA
grg_pheno_sim-1.4.dist-info/WHEEL
grg_pheno_sim-1.4.dist-info/top_level.txt
grg_pheno_sim-1.4.dist-info/RECORD
