Metadata-Version: 2.4
Name: grg_pheno_sim
Version: 1.4
Summary: Phenotype simulator for GRGs
Home-page: https://aprilweilab.github.io/
Author: Aditya Syam
Author-email: 
Classifier: Programming Language :: Python :: 3
Classifier: Programming Language :: Python :: 3.9
Classifier: Programming Language :: Python :: 3.10
Classifier: Programming Language :: Python :: 3.11
Classifier: Programming Language :: Python :: 3.12
Classifier: Programming Language :: Python :: 3.13
License-File: LICENSE
Requires-Dist: numpy>=2.0.2
Requires-Dist: pandas>=2.2.3
Requires-Dist: pygrgl>=2.3
Requires-Dist: scipy>=1.13.1
Dynamic: author
Dynamic: classifier
Dynamic: description
Dynamic: description-content-type
Dynamic: home-page
Dynamic: license-file
Dynamic: requires-dist
Dynamic: summary
